MANIFEST.in
README
setup.py
django_widgets/__init__.py
django_widgets/widgets.py
django_widgets.egg-info/PKG-INFO
django_widgets.egg-info/SOURCES.txt
django_widgets.egg-info/dependency_links.txt
django_widgets.egg-info/not-zip-safe
django_widgets.egg-info/requires.txt
django_widgets.egg-info/top_level.txt
django_widgets/static/django-widgets.css
django_widgets/static/django-widgets.js
django_widgets/templates/djangowidgets/autocompleteselect.html
django_widgets/templates/djangowidgets/buttonselect.html
django_widgets/templates/djangowidgets/buttonselectinput.html